README.rst
setup.py
simpleazure/__init__.py
simpleazure/ansible_api.py
simpleazure/azure_network_management.py
simpleazure/azure_quickstart_templates.py
simpleazure/azure_resource_manager.py
simpleazure/azure_service_management.py
simpleazure/cli.py
simpleazure/cluster.py
simpleazure/config.py
simpleazure/github_api.py
simpleazure/github_cli.py
simpleazure/simpleazure.py
simpleazure/ssh.py
simpleazure/sshkey.py
simpleazure/utils.py
simpleazure/vmdepot.py
simpleazure.egg-info/PKG-INFO
simpleazure.egg-info/SOURCES.txt
simpleazure.egg-info/dependency_links.txt
simpleazure.egg-info/entry_points.txt
simpleazure.egg-info/requires.txt
simpleazure.egg-info/top_level.txt
simpleazure/ext/__init__.py
simpleazure/ext/credentials.py
simpleazure/plugin/__init__.py
simpleazure/plugin/ipython.py
simpleazure/template/__init__.py
simpleazure/template/compile.py
simpleazure/template/reader.py
simpleazure/template/template.py