Metadata-Version: 1.1
Name: simpleazure
Version: 0.1.5
Summary: Python Library for Windows Azure
Home-page: http://simple-azure.readthedocs.io/
Author: Hyungro Lee
Author-email: hroe.lee@gmail.com
License: GPLv3
Keywords: SimpleAzure,Azure,Template deployment
Platform: UNKNOWN
Classifier: Development Status :: 3 - Alpha
Classifier: Topic :: Scientific/Engineering
Classifier: Intended Audience :: Developers
Classifier: Intended Audience :: Science/Research
Classifier: License :: OSI Approved :: GNU General Public License v3 (GPLv3)
Classifier: Operating System :: POSIX :: Linux
Classifier: Programming Language :: Python
